somnium/__init__.py
somnium/__main__.py
somnium/sync/__init__.py
somnium/sync/__main__.py
somnium-9.9.4.dist-info/LICENSE
somnium-9.9.4.dist-info/METADATA
somnium-9.9.4.dist-info/WHEEL
somnium-9.9.4.dist-info/top_level.txt
somnium-9.9.4.dist-info/RECORD
