Metadata-Version: 2.1
Name: somnium
Version: 9.9.4
Summary: Create beautiful artwork using the power of AI.
Home-page: https://t.me/execal
Author: odi
Author-email: ivuxey@gmail.com
License: MIT
Project-URL: Source, https://github.com/vauth
Project-URL: Bug Tracker, https://t.me/feelded
Keywords: ai,stablediffusion,dream,somnium
Classifier: Programming Language :: Python :: 3
Classifier: License :: OSI Approved :: MIT License
Classifier: Operating System :: OS Independent
Requires-Python: >=3.5
License-File: LICENSE
Requires-Dist: html-telegraph-poster
Requires-Dist: lxml-html-clean
